Metadata-Version: 1.0
Name: useful-distributions
Version: 0.1
Summary: Gaussian and Binomial distributions
Home-page: UNKNOWN
Author: ['Kianna Hendricks']
Author-email: UNKNOWN
License: UNKNOWN
Platform: UNKNOWN
